supynote/__init__.py
supynote/cli.py
supynote/converter.py
supynote/device_finder.py
supynote/merger.py
supynote/pdf_merger.py
supynote/supernote.py
supynote/application/__init__.py
supynote/application/dtos/browse_dto.py
supynote/application/dtos/device_dto.py
supynote/application/dtos/device_info_dto.py
supynote/application/dtos/download_dto.py
supynote/application/dtos/list_files_dto.py
supynote/application/use_cases/browse_device.py
supynote/application/use_cases/download_use_case.py
supynote/application/use_cases/find_device.py
supynote/application/use_cases/get_device_info.py
supynote/application/use_cases/list_files.py
supynote/domain/__init__.py
supynote/domain/device_management/__init__.py
supynote/domain/device_management/entities/device.py
supynote/domain/device_management/repositories/device_repository.py
supynote/domain/device_management/value_objects/device_connection.py
supynote/domain/note_management/__init__.py
supynote/domain/note_management/entities/note.py
supynote/domain/note_management/repositories/note_repository.py
supynote/domain/note_management/services/conversion_service.py
supynote/domain/note_management/value_objects/note_id.py
supynote/domain/note_management/value_objects/note_path.py
supynote/domain/note_management/value_objects/time_range_filter.py
supynote/domain/shared/__init__.py
supynote/domain/shared/base_entity.py
supynote/domain/shared/base_value_object.py
supynote/infrastructure/__init__.py
supynote/infrastructure/network/network_discovery_service.py
supynote/infrastructure/repositories/memory_device_repository.py
supynote/infrastructure/repositories/supernote_remote_repository.py
supynote/ocr/__init__.py
supynote/ocr/entities.py
supynote/ocr/llava_service.py
supynote/ocr/native_service.py
supynote/ocr/pdf_processor.py
supynote/ocr/services.py
supynote/ocr/trocr_service.py
supynote/presentation/__init__.py
supynote/presentation/cli/__init__.py
supynote/presentation/cli/container.py
supynote/presentation/cli/dispatcher.py
supynote-0.9.1.dist-info/METADATA
supynote-0.9.1.dist-info/WHEEL
supynote-0.9.1.dist-info/entry_points.txt
supynote-0.9.1.dist-info/licenses/LICENSE
supynote-0.9.1.dist-info/RECORD
