Metadata-Version: 2.4
Name: supynote
Version: 0.9.1
Summary: A simple CLI tool to interact with Supernote devices
Project-URL: Homepage, https://github.com/thopiax/supynote
Project-URL: Repository, https://github.com/thopiax/supynote
Project-URL: Issues, https://github.com/thopiax/supynote/issues
Author-email: Rafael Ballestiero <rafaba@hey.com>
License: MIT
License-File: LICENSE
Keywords: cli,e-ink,markdown,note-taking,ocr,pdf,supernote
Classifier: Development Status :: 4 - Beta
Classifier: Intended Audience :: End Users/Desktop
Classifier: License :: OSI Approved :: MIT License
Classifier: Programming Language :: Python :: 3
Classifier: Programming Language :: Python :: 3.8
Classifier: Programming Language :: Python :: 3.9
Classifier: Programming Language :: Python :: 3.10
Classifier: Programming Language :: Python :: 3.11
Classifier: Programming Language :: Python :: 3.12
Classifier: Topic :: Utilities
Requires-Python: >=3.8.1
Requires-Dist: aiofiles>=23.0.0
Requires-Dist: aiohttp>=3.8.0
Requires-Dist: beautifulsoup4>=4.9.0
Requires-Dist: pypdf>=5.9.0
Requires-Dist: requests>=2.25.0
Requires-Dist: supernotelib>=0.6.0
Provides-Extra: dev
Requires-Dist: black>=23.0.0; extra == 'dev'
Requires-Dist: flake8>=6.0.0; extra == 'dev'
Requires-Dist: pytest>=8.3.5; extra == 'dev'
Provides-Extra: ocr
Requires-Dist: numpy>=1.24.4; extra == 'ocr'
Requires-Dist: opencv-python>=4.8.0; extra == 'ocr'
Requires-Dist: pillow>=10.4.0; extra == 'ocr'
Requires-Dist: pymupdf>=1.24.11; extra == 'ocr'
Requires-Dist: torch>=2.5.1; extra == 'ocr'
Requires-Dist: torchvision>=0.20.1; extra == 'ocr'
Requires-Dist: transformers>=4.46.3; extra == 'ocr'
